pybabel_angularjs/__init__.py
pybabel_angularjs/extractor.py
pybabel_angularjs-1.2.0.dist-info/METADATA
pybabel_angularjs-1.2.0.dist-info/RECORD
pybabel_angularjs-1.2.0.dist-info/WHEEL
pybabel_angularjs-1.2.0.dist-info/entry_points.txt
pybabel_angularjs-1.2.0.dist-info/top_level.txt
