Metadata-Version: 2.1
Name: pybabel-angularjs
Version: 1.2.0
Summary: An AngularJS extractor for Babel
Home-page: https://github.com/chuckyblack/pybabel-angularjs
Author: Jaromír Pufler
Author-email: jaromir.pufler@gmail.com
License: Apache Software License
Keywords: angularjs gettext babel i18n translate
Platform: UNKNOWN
Classifier: Development Status :: 5 - Production/Stable
Classifier: Intended Audience :: Developers
Classifier: Topic :: Software Development :: Internationalization
Classifier: License :: OSI Approved :: Apache Software License
Classifier: Operating System :: OS Independent
Classifier: Programming Language :: Python
Classifier: Programming Language :: Python :: 2
Classifier: Programming Language :: Python :: 2.6
Classifier: Programming Language :: Python :: 2.7
Classifier: Programming Language :: Python :: 3
Classifier: Programming Language :: Python :: 3.2
Classifier: Programming Language :: Python :: 3.3
Classifier: Programming Language :: Python :: 3.4
Classifier: Programming Language :: Python :: 3.5
Requires-Dist: babel
Requires-Dist: beautifulsoup4
